grpc_messenger/__init__.py
grpc_messenger/backend.py
grpc_messenger/pipes.py
grpc_messenger/protos/__init__.py
grpc_messenger/protos/Messager_pb2.py
grpc_messenger/protos/Messager_pb2.pyi
grpc_messenger/protos/Messager_pb2_grpc.py
grpc_messenger/view_interfaces.py
grpc_messenger-1.0.1.dist-info/METADATA
grpc_messenger-1.0.1.dist-info/WHEEL
grpc_messenger-1.0.1.dist-info/RECORD
