Metadata-Version: 2.1
Name: grpc-messenger
Version: 1.0.1
Summary: Send text messages over the network, using grpc
Home-page: https://github.com/IgnaciodelaTorreArias/grpc-messenger
License: MIT
Author: Ignacio de la Torre
Author-email: ignaciodlta@gmail.com
Maintainer: Ignacio de la Torre
Maintainer-email: ignaciodlta@gmail.com
Requires-Python: >=3.12,<4.0
Classifier: Framework :: AsyncIO
Classifier: Intended Audience :: Developers
Classifier: License :: OSI Approved :: MIT License
Classifier: Natural Language :: English
Classifier: Programming Language :: Python :: 3
Classifier: Programming Language :: Python :: 3.12
Classifier: Topic :: Communications
Classifier: Topic :: Communications :: Chat
Classifier: Topic :: Software Development :: Libraries :: Application Frameworks
Classifier: Topic :: Software Development :: Libraries :: Python Modules
Classifier: Topic :: Software Development :: User Interfaces
Classifier: Typing :: Typed
Requires-Dist: grpcio (>=1.65.4,<2.0.0)
Requires-Dist: protobuf (>=5.27.3,<6.0.0)
Project-URL: Repository, https://github.com/IgnaciodelaTorreArias/grpc-messenger
